stats_arrays/__init__.py
stats_arrays/dataset_statistics.py
stats_arrays/errors.py
stats_arrays/random.py
stats_arrays/uncertainty_choices.py
stats_arrays/utils.py
stats_arrays/distributions/__init__.py
stats_arrays/distributions/base.py
stats_arrays/distributions/bernoulli.py
stats_arrays/distributions/beta.py
stats_arrays/distributions/beta_pert.py
stats_arrays/distributions/discrete_uniform.py
stats_arrays/distributions/extreme.py
stats_arrays/distributions/gamma.py
stats_arrays/distributions/geometric.py
stats_arrays/distributions/lognormal.py
stats_arrays/distributions/normal.py
stats_arrays/distributions/student.py
stats_arrays/distributions/undefined.py
stats_arrays/distributions/weibull.py
stats_arrays-0.8.dist-info/licenses/LICENSE
stats_arrays-0.8.dist-info/METADATA
stats_arrays-0.8.dist-info/WHEEL
stats_arrays-0.8.dist-info/top_level.txt
stats_arrays-0.8.dist-info/RECORD
