Metadata-Version: 2.4
Name: stats_arrays
Version: 0.8
Summary: Standard NumPy array interface for defining uncertain parameters
Author-email: Chris Mutel <cmutel@gmail.com>
Maintainer-email: Chris Mutel <cmutel@gmail.com>
Project-URL: source, https://github.com/brightway-lca/stats_arrays
Project-URL: homepage, https://github.com/brightway-lca/stats_arrays
Project-URL: tracker, https://github.com/brightway-lca/stats_arrays/issues
Classifier: Development Status :: 4 - Beta
Classifier: Programming Language :: Python
Classifier: Programming Language :: Python :: 3
Classifier: Programming Language :: Python :: 3.9
Classifier: Programming Language :: Python :: 3.10
Classifier: Programming Language :: Python :: 3.11
Classifier: Programming Language :: Python :: 3.12
Classifier: Programming Language :: Python :: 3.13
Classifier: Programming Language :: Python :: 3.14
Classifier: Natural Language :: English
Classifier: Operating System :: OS Independent
Classifier: Topic :: Scientific/Engineering
Requires-Python: >=3.9
License-File: LICENSE
Requires-Dist: numpy>=1.6.0
Requires-Dist: scipy>=1.1.0
Provides-Extra: testing
Requires-Dist: stats_arrays; extra == "testing"
Requires-Dist: pytest; extra == "testing"
Requires-Dist: pytest-cov; extra == "testing"
Requires-Dist: python-coveralls; extra == "testing"
Provides-Extra: dev
Requires-Dist: build; extra == "dev"
Requires-Dist: pre-commit; extra == "dev"
Requires-Dist: pylint; extra == "dev"
Requires-Dist: pytest; extra == "dev"
Requires-Dist: pytest-cov; extra == "dev"
Requires-Dist: pytest-randomly; extra == "dev"
Requires-Dist: setuptools; extra == "dev"
Dynamic: license-file
